dangam/__init__.py
dangam/config.py
dangam/dangam.py
DanGam-0.1.2.dist-info/LICENSE
DanGam-0.1.2.dist-info/METADATA
DanGam-0.1.2.dist-info/WHEEL
DanGam-0.1.2.dist-info/top_level.txt
DanGam-0.1.2.dist-info/RECORD
